django_forcedfields.py
django_forcedfields-1.0.1.dist-info/DESCRIPTION.rst
django_forcedfields-1.0.1.dist-info/METADATA
django_forcedfields-1.0.1.dist-info/RECORD
django_forcedfields-1.0.1.dist-info/WHEEL
django_forcedfields-1.0.1.dist-info/metadata.json
django_forcedfields-1.0.1.dist-info/top_level.txt
