Metadata-Version: 2.0
Name: django-forcedfields
Version: 1.0.1
Summary: Django model fields designed to more precisely and semantically define data types.
Home-page: https://github.com/monotonee/django-forcedfields
Author: monotonee
Author-email: monotonee@tuta.io
License: MIT
Keywords: char database django field model timestamp
Platform: UNKNOWN
Classifier: Development Status :: 5 - Production/Stable
Classifier: Framework :: Django
Classifier: Intended Audience :: Developers
Classifier: License :: OSI Approved :: MIT License
Classifier: Natural Language :: English
Classifier: Programming Language :: Python :: 3 :: Only
Classifier: Topic :: Database
Requires-Dist: django
Provides-Extra: dev
Requires-Dist: docker-compose; extra == 'dev'
Requires-Dist: mysqlclient; extra == 'dev'
Requires-Dist: psycopg2-binary; extra == 'dev'
Requires-Dist: pylint; extra == 'dev'
Requires-Dist: twine; extra == 'dev'
Requires-Dist: wheel; extra == 'dev'
